pyiodine/__init__.py
pyiodine/ahr_model.py
pyiodine/cli.py
pyiodine-0.2.0.dist-info/AUTHORS.rst
pyiodine-0.2.0.dist-info/LICENSE
pyiodine-0.2.0.dist-info/METADATA
pyiodine-0.2.0.dist-info/WHEEL
pyiodine-0.2.0.dist-info/entry_points.txt
pyiodine-0.2.0.dist-info/top_level.txt
pyiodine-0.2.0.dist-info/RECORD
