Metadata-Version: 2.1
Name: pyiodine
Version: 0.2.0
Summary: A kinetic model of the AHR and its regulation
Home-page: https://github.com/dileep-kishore/Iodine
Author: Dileep Kishore
Author-email: dkishore@bu.edu
License: MIT license
Keywords: pyiodine
Platform: UNKNOWN
Classifier: Development Status :: 2 - Pre-Alpha
Classifier: Intended Audience :: Developers
Classifier: License :: OSI Approved :: MIT License
Classifier: Natural Language :: English
Classifier: Programming Language :: Python :: 3.6
Requires-Dist: tellurium
Requires-Dist: sympy
Requires-Dist: click
Requires-Dist: halo
Requires-Dist: seaborn
